.DS_Store
super_grep/__init__.py
super_grep/main.py
super_grep-0.1.9.dist-info/LICENSE
super_grep-0.1.9.dist-info/METADATA
super_grep-0.1.9.dist-info/WHEEL
super_grep-0.1.9.dist-info/entry_points.txt
super_grep-0.1.9.dist-info/top_level.txt
super_grep-0.1.9.dist-info/RECORD
