Metadata-Version: 2.1
Name: super-grep
Version: 0.1.9
Summary: A powerful, format-agnostic search tool
Home-page: https://github.com/msmolkin/super-grep
Author: Michael Smolkin
Author-email: michael@smolkin.org
Classifier: Development Status :: 3 - Alpha
Classifier: Intended Audience :: Developers
Classifier: License :: OSI Approved :: MIT License
Classifier: Operating System :: OS Independent
Classifier: Programming Language :: Python :: 3
Classifier: Programming Language :: Python :: 3.6
Classifier: Programming Language :: Python :: 3.7
Classifier: Programming Language :: Python :: 3.8
Classifier: Programming Language :: Python :: 3.9
Requires-Python: >=3.6
License-File: LICENSE
